[
    {
        "id": 632,
        "name": "Afijio",
        "state_id": 296,
        "state_code": "OY",
        "state_name": "Oyo",
        "country_id": 161,
        "country_code": "NG",
        "country_name": "Nigeria",
        "latitude": 7.8,
        "longitude": 3.9,
        "wikiDataId": "Q4689246"
    },
    {
        "id": 633,
        "name": "Akinyele",
        "state_id": 296,
        "state_code": "OY",
        "state_name": "Oyo",
        "country_id": 161,
        "country_code": "NG",
        "country_name": "Nigeria",
        "latitude": 7.523735,
        "longitude": 3.914781,
        "wikiDataId": "Q4701091"
    },
    {
        "id": 634,
        "name": "Atiba",
        "state_id": 296,
        "state_code": "OY",
        "state_name": "Oyo",
        "country_id": 161,
        "country_code": "NG",
        "country_name": "Nigeria",
        "latitude": 7.849454,
        "longitude": 3.930354,
        "wikiDataId": "Q4815763"
    },
    {
        "id": 635,
        "name": "Atisbo",
        "state_id": 296,
        "state_code": "OY",
        "state_name": "Oyo",
        "country_id": 161,
        "country_code": "NG",
        "country_name": "Nigeria",
        "latitude": 8.549788,
        "longitude": 3.45,
        "wikiDataId": "Q4815853"
    },
    {
        "id": 636,
        "name": "Egbeda",
        "state_id": 296,
        "state_code": "OY",
        "state_name": "Oyo",
        "country_id": 161,
        "country_code": "NG",
        "country_name": "Nigeria",
        "latitude": 7.381337,
        "longitude": 3.966501,
        "wikiDataId": "Q5347703"
    },
    {
        "id": 637,
        "name": "Ibadan North",
        "state_id": 296,
        "state_code": "OY",
        "state_name": "Oyo",
        "country_id": 161,
        "country_code": "NG",
        "country_name": "Nigeria",
        "latitude": 7.403239,
        "longitude": 3.913107,
        "wikiDataId": "Q5983592"
    },
    {
        "id": 638,
        "name": "Ibadan North East",
        "state_id": 296,
        "state_code": "OY",
        "state_name": "Oyo",
        "country_id": 161,
        "country_code": "NG",
        "country_name": "Nigeria",
        "latitude": 7.401536,
        "longitude": 3.938985,
        "wikiDataId": "Q5983595"
    },
    {
        "id": 639,
        "name": "Ibadan North West",
        "state_id": 296,
        "state_code": "OY",
        "state_name": "Oyo",
        "country_id": 161,
        "country_code": "NG",
        "country_name": "Nigeria",
        "latitude": 7.395799,
        "longitude": 3.881569,
        "wikiDataId": "Q5983588"
    },
    {
        "id": 640,
        "name": "Ibadan South East",
        "state_id": 296,
        "state_code": "OY",
        "state_name": "Oyo",
        "country_id": 161,
        "country_code": "NG",
        "country_name": "Nigeria",
        "latitude": 7.37577,
        "longitude": 3.897557,
        "wikiDataId": "Q11058510"
    },
    {
        "id": 641,
        "name": "Ibadan South West",
        "state_id": 296,
        "state_code": "OY",
        "state_name": "Oyo",
        "country_id": 161,
        "country_code": "NG",
        "country_name": "Nigeria",
        "latitude": 7.396389,
        "longitude": 3.916667,
        "wikiDataId": "Q5983608"
    },
    {
        "id": 642,
        "name": "Ibarapa Central",
        "state_id": 296,
        "state_code": "OY",
        "state_name": "Oyo",
        "country_id": 161,
        "country_code": "NG",
        "country_name": "Nigeria",
        "latitude": 7.435346,
        "longitude": 3.288581,
        "wikiDataId": "Q11290392"
    },
    {
        "id": 643,
        "name": "Ibarapa East",
        "state_id": 296,
        "state_code": "OY",
        "state_name": "Oyo",
        "country_id": 161,
        "country_code": "NG",
        "country_name": "Nigeria",
        "latitude": 7.549722,
        "longitude": 3.45,
        "wikiDataId": "Q11290895"
    },
    {
        "id": 644,
        "name": "Ibarapa North",
        "state_id": 296,
        "state_code": "OY",
        "state_name": "Oyo",
        "country_id": 161,
        "country_code": "NG",
        "country_name": "Nigeria",
        "latitude": 7.564226,
        "longitude": 3.229916,
        "wikiDataId": "Q5983733"
    },
    {
        "id": 645,
        "name": "Ido",
        "state_id": 296,
        "state_code": "OY",
        "state_name": "Oyo",
        "country_id": 161,
        "country_code": "NG",
        "country_name": "Nigeria",
        "latitude": 7.507354,
        "longitude": 3.719376,
        "wikiDataId": "Q3331530"
    },
    {
        "id": 646,
        "name": "Irepo",
        "state_id": 296,
        "state_code": "OY",
        "state_name": "Oyo",
        "country_id": 161,
        "country_code": "NG",
        "country_name": "Nigeria",
        "latitude": 7.350425,
        "longitude": 3.880304,
        "wikiDataId": "Q6069380"
    },
    {
        "id": 647,
        "name": "Iseyin",
        "state_id": 296,
        "state_code": "OY",
        "state_name": "Oyo",
        "country_id": 161,
        "country_code": "NG",
        "country_name": "Nigeria",
        "latitude": 7.96666667,
        "longitude": 3.6,
        "wikiDataId": "Q1673881"
    },
    {
        "id": 648,
        "name": "Itesiwaju",
        "state_id": 296,
        "state_code": "OY",
        "state_name": "Oyo",
        "country_id": 161,
        "country_code": "NG",
        "country_name": "Nigeria",
        "latitude": 7.358763,
        "longitude": 3.959258,
        "wikiDataId": "Q6094439"
    },
    {
        "id": 649,
        "name": "Iwajowa",
        "state_id": 296,
        "state_code": "OY",
        "state_name": "Oyo",
        "country_id": 161,
        "country_code": "NG",
        "country_name": "Nigeria",
        "latitude": 7.983269,
        "longitude": 3.05274,
        "wikiDataId": "Q6100332"
    },
    {
        "id": 650,
        "name": "Kajola",
        "state_id": 296,
        "state_code": "OY",
        "state_name": "Oyo",
        "country_id": 161,
        "country_code": "NG",
        "country_name": "Nigeria",
        "latitude": 8.037685,
        "longitude": 3.348942,
        "wikiDataId": "Q11282187"
    },
    {
        "id": 651,
        "name": "Lagelu",
        "state_id": 296,
        "state_code": "OY",
        "state_name": "Oyo",
        "country_id": 161,
        "country_code": "NG",
        "country_name": "Nigeria",
        "latitude": 7.495026,
        "longitude": 4.073009,
        "wikiDataId": "Q6471977"
    },
    {
        "id": 652,
        "name": "Ogbomosho North",
        "state_id": 296,
        "state_code": "OY",
        "state_name": "Oyo",
        "country_id": 161,
        "country_code": "NG",
        "country_name": "Nigeria",
        "latitude": 8.133333,
        "longitude": 4.25,
        "wikiDataId": "Q7079884"
    },
    {
        "id": 653,
        "name": "Ogbomosho South",
        "state_id": 296,
        "state_code": "OY",
        "state_name": "Oyo",
        "country_id": 161,
        "country_code": "NG",
        "country_name": "Nigeria",
        "latitude": 8.11791,
        "longitude": 4.239092,
        "wikiDataId": "Q7079886"
    },
    {
        "id": 654,
        "name": "Ogo Oluwa",
        "state_id": 296,
        "state_code": "OY",
        "state_name": "Oyo",
        "country_id": 161,
        "country_code": "NG",
        "country_name": "Nigeria",
        "latitude": 8.13524,
        "longitude": 4.24006,
        "wikiDataId": "Q7080182"
    },
    {
        "id": 655,
        "name": "Olorunsogo",
        "state_id": 296,
        "state_code": "OY",
        "state_name": "Oyo",
        "country_id": 161,
        "country_code": "NG",
        "country_name": "Nigeria",
        "latitude": 8.752377,
        "longitude": 4.130988,
        "wikiDataId": "Q7088523"
    },
    {
        "id": 656,
        "name": "Oluyole",
        "state_id": 296,
        "state_code": "OY",
        "state_name": "Oyo",
        "country_id": 161,
        "country_code": "NG",
        "country_name": "Nigeria",
        "latitude": 7.218,
        "longitude": 3.892,
        "wikiDataId": "Q7088882"
    },
    {
        "id": 657,
        "name": "Ona Ara",
        "state_id": 296,
        "state_code": "OY",
        "state_name": "Oyo",
        "country_id": 161,
        "country_code": "NG",
        "country_name": "Nigeria",
        "latitude": 7.225568,
        "longitude": 4.026554,
        "wikiDataId": "Q11275966"
    },
    {
        "id": 658,
        "name": "Oorelope",
        "state_id": 296,
        "state_code": "OY",
        "state_name": "Oyo",
        "country_id": 161,
        "country_code": "NG",
        "country_name": "Nigeria",
        "latitude": 8.833333,
        "longitude": 3.75,
        "wikiDataId": "Q7101528"
    },
    {
        "id": 659,
        "name": "Ori Ire",
        "state_id": 296,
        "state_code": "OY",
        "state_name": "Oyo",
        "country_id": 161,
        "country_code": "NG",
        "country_name": "Nigeria",
        "latitude": 8.33423,
        "longitude": 4.14423,
        "wikiDataId": "Q7102202"
    },
    {
        "id": 660,
        "name": "Oyo East",
        "state_id": 296,
        "state_code": "OY",
        "state_name": "Oyo",
        "country_id": 161,
        "country_code": "NG",
        "country_name": "Nigeria",
        "latitude": 7.882092,
        "longitude": 3.998755,
        "wikiDataId": "Q7116295"
    },
    {
        "id": 661,
        "name": "Oyo West",
        "state_id": 296,
        "state_code": "OY",
        "state_name": "Oyo",
        "country_id": 161,
        "country_code": "NG",
        "country_name": "Nigeria",
        "latitude": 7.94157,
        "longitude": 3.8218,
        "wikiDataId": "Q7116297"
    },
    {
        "id": 662,
        "name": "Saki East",
        "state_id": 296,
        "state_code": "OY",
        "state_name": "Oyo",
        "country_id": 161,
        "country_code": "NG",
        "country_name": "Nigeria",
        "latitude": 8.628418,
        "longitude": 3.640723,
        "wikiDataId": "Q7402968"
    },
    {
        "id": 663,
        "name": "Saki West",
        "state_id": 296,
        "state_code": "OY",
        "state_name": "Oyo",
        "country_id": 161,
        "country_code": "NG",
        "country_name": "Nigeria",
        "latitude": 8.666667,
        "longitude": 3.4,
        "wikiDataId": "Q7402971"
    },
    {
        "id": 664,
        "name": "Surulere",
        "state_id": 296,
        "state_code": "OY",
        "state_name": "Oyo",
        "country_id": 161,
        "country_code": "NG",
        "country_name": "Nigeria",
        "latitude": 6.5,
        "longitude": 3.35,
        "wikiDataId": "Q994119"
    }
]